automl_optuna_demo/__init__.py
automl_optuna_demo/main.py
automl_optuna_demo-0.1.1.dist-info/METADATA
automl_optuna_demo-0.1.1.dist-info/WHEEL
automl_optuna_demo-0.1.1.dist-info/top_level.txt
automl_optuna_demo-0.1.1.dist-info/RECORD
