Metadata-Version: 2.4
Name: automl_optuna_demo
Version: 0.1.1
Summary: A simple AutoML demo using Optuna and Scikit-learn
Author: Vaishnav Naik
Requires-Python: >=3.8
Requires-Dist: optuna
Requires-Dist: scikit-learn
Dynamic: author
Dynamic: description
Dynamic: description-content-type
Dynamic: requires-dist
Dynamic: requires-python
Dynamic: summary
